{"batter": "testuser", "pitches": [{"GameDate": "2026-04-15", "PitcherHand": "L", "PitchType": "Sinker", "Balls": 3, "Strikes": 0, "PlateLocHeight": 3.627611787559899, "PlateLocSide": 0.10276945970136664, "PlayResult": "Out", "xwOBA": 1.0390531875323514}, {"GameDate": "2026-04-10", "PitcherHand": "L", "PitchType": "Changeup", "Balls": 2, "Strikes": 0, "PlateLocHeight": 4.334095077413881, "PlateLocSide": -1.388802627304804, "PlayResult": "Out", "xwOBA": 0.5426363652079048}, {"GameDate": "2026-04-01", "PitcherHand": "R", "PitchType": "Fastball", "Balls": 2, "Strikes": 2, "PlateLocHeight": 0.8064452316339512, "PlateLocSide": 0.779581667753749, "PlayResult": "Double", "xwOBA": 0.16423153863858347}, {"GameDate": "2026-04-03", "PitcherHand": "R", "PitchType": "Sinker", "Balls": 2, "Strikes": 2, "PlateLocHeight": 4.441146644582755, "PlateLocSide": -1.4528302026597366, "PlayResult": "Double", "xwOBA": 1.0572826053564983}, {"GameDate": "2026-04-03", "PitcherHand": "R", "PitchType": "Changeup", "Balls": 0, "Strikes": 2, "PlateLocHeight": 2.150769471061074, "PlateLocSide": 0.23727598046516607, "PlayResult": "HomeRun", "xwOBA": 0.21194436969743613}, {"GameDate": "2026-04-15", "PitcherHand": "R", "PitchType": "Curveball", "Balls": 1, "Strikes": 1, "PlateLocHeight": 0.8799132055951375, "PlateLocSide": 1.4327395347428293, "PlayResult": "Single", "xwOBA": 0.9925927861795216}, {"GameDate": "2026-04-07", "PitcherHand": "L", "PitchType": "Sinker", "Balls": 3, "Strikes": 2, "PlateLocHeight": 2.1852903638339134, "PlateLocSide": -0.13200636222635032, "PlayResult": "Double", "xwOBA": 1.4645334242938475}, {"GameDate": "2026-04-07", "PitcherHand": "L", "PitchType": "Slider", "Balls": 1, "Strikes": 0, "PlateLocHeight": 1.4697422356707759, "PlateLocSide": 0.8941327705417139, "PlayResult": "Out", "xwOBA": 0.9434633626855454}, {"GameDate": "2026-04-03", "PitcherHand": "L", "PitchType": "Changeup", "Balls": 0, "Strikes": 0, "PlateLocHeight": 1.3182584028534605, "PlateLocSide": 0.6635479592748554, "PlayResult": "Out", "xwOBA": 0.4757476354905703}, {"GameDate": "2026-04-05", "PitcherHand": "L", "PitchType": "Fastball", "Balls": 0, "Strikes": 0, "PlateLocHeight": 1.900938672892365, "PlateLocSide": -1.0938115813981808, "PlayResult": "HomeRun", "xwOBA": 1.2871654831129}, {"GameDate": "2026-04-05", "PitcherHand": "L", "PitchType": "Slider", "Balls": 3, "Strikes": 2, "PlateLocHeight": 4.293517522544541, "PlateLocSide": 0.37178874768344383, "PlayResult": "Out", "xwOBA": 1.0468303560793486}, {"GameDate": "2026-04-10", "PitcherHand": "L", "PitchType": "Slider", "Balls": 1, "Strikes": 1, "PlateLocHeight": 2.132719877431312, "PlateLocSide": -0.5174085944637933, "PlayResult": "Out", "xwOBA": 1.0765150058575663}, {"GameDate": "2026-04-10", "PitcherHand": "L", "PitchType": "Sinker", "Balls": 3, "Strikes": 0, "PlateLocHeight": 0.562436355164643, "PlateLocSide": -0.27229944247238747, "PlayResult": "Out", "xwOBA": 0.28621251153926075}, {"GameDate": "2026-04-10", "PitcherHand": "L", "PitchType": "Curveball", "Balls": 2, "Strikes": 2, "PlateLocHeight": 3.1585449615124834, "PlateLocSide": 1.4159049603171607, "PlayResult": "Out", "xwOBA": 0.1287010344768112}, {"GameDate": "2026-04-05", "PitcherHand": "L", "PitchType": "Changeup", "Balls": 1, "Strikes": 2, "PlateLocHeight": 3.320457175250998, "PlateLocSide": -0.0824631306966368, "PlayResult": "HomeRun", "xwOBA": 0.3235931517566023}, {"GameDate": "2026-04-07", "PitcherHand": "L", "PitchType": "Changeup", "Balls": 3, "Strikes": 2, "PlateLocHeight": 1.9234669455017235, "PlateLocSide": 1.395002680664649, "PlayResult": "Double", "xwOBA": 0.5845011212619267}, {"GameDate": "2026-04-15", "PitcherHand": "L", "PitchType": "Slider", "Balls": 3, "Strikes": 0, "PlateLocHeight": 3.784923994404181, "PlateLocSide": -0.7513759707683014, "PlayResult": "Double", "xwOBA": 1.043529776404177}, {"GameDate": "2026-04-15", "PitcherHand": "R", "PitchType": "Changeup", "Balls": 1, "Strikes": 0, "PlateLocHeight": 2.5703321279768767, "PlateLocSide": -1.401324668361166, "PlayResult": "Double", "xwOBA": 0.7285566226727163}, {"GameDate": "2026-04-07", "PitcherHand": "L", "PitchType": "Changeup", "Balls": 3, "Strikes": 0, "PlateLocHeight": 0.7842582507147018, "PlateLocSide": -1.1353467129263501, "PlayResult": "Double", "xwOBA": 0.13344080964050037}, {"GameDate": "2026-04-10", "PitcherHand": "L", "PitchType": "Changeup", "Balls": 1, "Strikes": 2, "PlateLocHeight": 1.645162318395906, "PlateLocSide": 0.7248308888745001, "PlayResult": "Out", "xwOBA": 0.3824936866424386}, {"GameDate": "2026-04-01", "PitcherHand": "R", "PitchType": "Sinker", "Balls": 3, "Strikes": 1, "PlateLocHeight": 0.5181799471713786, "PlateLocSide": 0.4510337978758474, "PlayResult": "Single", "xwOBA": 0.37945247861119147}, {"GameDate": "2026-04-07", "PitcherHand": "L", "PitchType": "Sinker", "Balls": 1, "Strikes": 1, "PlateLocHeight": 1.833692629665475, "PlateLocSide": 0.8386852546688703, "PlayResult": "Double", "xwOBA": 1.3698595911198868}, {"GameDate": "2026-04-01", "PitcherHand": "L", "PitchType": "Changeup", "Balls": 0, "Strikes": 1, "PlateLocHeight": 4.204082470842879, "PlateLocSide": 1.4649687810231646, "PlayResult": "HomeRun", "xwOBA": 0.8740802798371563}, {"GameDate": "2026-04-07", "PitcherHand": "R", "PitchType": "Changeup", "Balls": 3, "Strikes": 0, "PlateLocHeight": 1.1877668307668348, "PlateLocSide": 0.7976099945070656, "PlayResult": "Out", "xwOBA": 1.3303322966295774}, {"GameDate": "2026-04-05", "PitcherHand": "R", "PitchType": "Curveball", "Balls": 2, "Strikes": 1, "PlateLocHeight": 4.069156112890227, "PlateLocSide": 0.22737251121286395, "PlayResult": "Out", "xwOBA": 1.221787415714383}, {"GameDate": "2026-04-01", "PitcherHand": "L", "PitchType": "Slider", "Balls": 3, "Strikes": 1, "PlateLocHeight": 1.9211052926956542, "PlateLocSide": 0.039042661056394756, "PlayResult": "Double", "xwOBA": 0.03693183588292548}, {"GameDate": "2026-04-01", "PitcherHand": "R", "PitchType": "Changeup", "Balls": 1, "Strikes": 0, "PlateLocHeight": 3.5067732590827596, "PlateLocSide": -1.2778518395725704, "PlayResult": "Single", "xwOBA": 0.7646779415329528}, {"GameDate": "2026-04-15", "PitcherHand": "L", "PitchType": "Changeup", "Balls": 3, "Strikes": 2, "PlateLocHeight": 1.6654487547178403, "PlateLocSide": 0.1820094504246743, "PlayResult": "Single", "xwOBA": 0.9019910679215933}, {"GameDate": "2026-04-07", "PitcherHand": "R", "PitchType": "Sinker", "Balls": 1, "Strikes": 1, "PlateLocHeight": 3.6715022969796665, "PlateLocSide": -0.11583172991610224, "PlayResult": "HomeRun", "xwOBA": 0.7859466959957697}, {"GameDate": "2026-04-01", "PitcherHand": "R", "PitchType": "Slider", "Balls": 1, "Strikes": 2, "PlateLocHeight": 3.095918400815405, "PlateLocSide": 0.13493911225264976, "PlayResult": "Out", "xwOBA": 0.3143834435960164}, {"GameDate": "2026-04-07", "PitcherHand": "R", "PitchType": "Curveball", "Balls": 0, "Strikes": 0, "PlateLocHeight": 1.6143500163335651, "PlateLocSide": 0.4625105979377657, "PlayResult": "Out", "xwOBA": 0.9662419193770906}, {"GameDate": "2026-04-05", "PitcherHand": "R", "PitchType": "Curveball", "Balls": 0, "Strikes": 1, "PlateLocHeight": 1.7895761062601294, "PlateLocSide": 1.4959510179708602, "PlayResult": "Out", "xwOBA": 1.477728973415987}, {"GameDate": "2026-04-01", "PitcherHand": "L", "PitchType": "Slider", "Balls": 1, "Strikes": 1, "PlateLocHeight": 1.20631876717218, "PlateLocSide": -1.2053845071934153, "PlayResult": "Single", "xwOBA": 0.6596887284569195}, {"GameDate": "2026-04-01", "PitcherHand": "R", "PitchType": "Changeup", "Balls": 0, "Strikes": 2, "PlateLocHeight": 2.420075001351123, "PlateLocSide": -0.08549034215407558, "PlayResult": "Single", "xwOBA": 1.3900084915860071}, {"GameDate": "2026-04-10", "PitcherHand": "R", "PitchType": "Slider", "Balls": 2, "Strikes": 0, "PlateLocHeight": 2.750052218638754, "PlateLocSide": 1.2860566432432585, "PlayResult": "Out", "xwOBA": 1.2795894385297486}, {"GameDate": "2026-04-15", "PitcherHand": "R", "PitchType": "Fastball", "Balls": 1, "Strikes": 0, "PlateLocHeight": 0.6088171400480675, "PlateLocSide": -1.1004183125833813, "PlayResult": "Out", "xwOBA": 0.2957167799291434}, {"GameDate": "2026-04-10", "PitcherHand": "R", "PitchType": "Changeup", "Balls": 1, "Strikes": 1, "PlateLocHeight": 4.1434869209460015, "PlateLocSide": 0.37980081016855927, "PlayResult": "Double", "xwOBA": 1.0767993585131228}, {"GameDate": "2026-04-01", "PitcherHand": "R", "PitchType": "Changeup", "Balls": 3, "Strikes": 1, "PlateLocHeight": 1.9611096235096181, "PlateLocSide": 0.20516148079136354, "PlayResult": "Out", "xwOBA": 1.457043292917015}, {"GameDate": "2026-04-05", "PitcherHand": "R", "PitchType": "Fastball", "Balls": 0, "Strikes": 0, "PlateLocHeight": 0.7068912534526275, "PlateLocSide": 0.9576709705214252, "PlayResult": "Out", "xwOBA": 0.4054490475426903}, {"GameDate": "2026-04-05", "PitcherHand": "R", "PitchType": "Curveball", "Balls": 3, "Strikes": 1, "PlateLocHeight": 1.389206105647935, "PlateLocSide": -1.3809850034731017, "PlayResult": "Out", "xwOBA": 0.3250034091906368}, {"GameDate": "2026-04-15", "PitcherHand": "R", "PitchType": "Curveball", "Balls": 0, "Strikes": 1, "PlateLocHeight": 2.3483767315188593, "PlateLocSide": -0.842634503016542, "PlayResult": "Out", "xwOBA": 0.020086568948002204}, {"GameDate": "2026-04-10", "PitcherHand": "L", "PitchType": "Slider", "Balls": 1, "Strikes": 1, "PlateLocHeight": 1.3389135118542863, "PlateLocSide": 0.3239539086062633, "PlayResult": "Single", "xwOBA": 0.8274449407711989}, {"GameDate": "2026-04-15", "PitcherHand": "R", "PitchType": "Curveball", "Balls": 1, "Strikes": 2, "PlateLocHeight": 2.180505405682271, "PlateLocSide": 1.183007940599869, "PlayResult": "Out", "xwOBA": 0.8235127575250393}, {"GameDate": "2026-04-05", "PitcherHand": "L", "PitchType": "Slider", "Balls": 1, "Strikes": 1, "PlateLocHeight": 2.5308059322200975, "PlateLocSide": 1.1500431563057325, "PlayResult": "Double", "xwOBA": 0.0024968842569761396}, {"GameDate": "2026-04-03", "PitcherHand": "L", "PitchType": "Curveball", "Balls": 0, "Strikes": 2, "PlateLocHeight": 3.75339212200096, "PlateLocSide": 1.19008839195754, "PlayResult": "HomeRun", "xwOBA": 1.2183833220680844}, {"GameDate": "2026-04-15", "PitcherHand": "L", "PitchType": "Changeup", "Balls": 2, "Strikes": 0, "PlateLocHeight": 3.1653052336990037, "PlateLocSide": -0.571063570665962, "PlayResult": "Double", "xwOBA": 0.4070045192570642}, {"GameDate": "2026-04-10", "PitcherHand": "L", "PitchType": "Fastball", "Balls": 1, "Strikes": 0, "PlateLocHeight": 3.938617557453818, "PlateLocSide": 0.9111001826755274, "PlayResult": "Out", "xwOBA": 1.2223998492891044}, {"GameDate": "2026-04-01", "PitcherHand": "R", "PitchType": "Fastball", "Balls": 0, "Strikes": 2, "PlateLocHeight": 1.3214509369325746, "PlateLocSide": 0.6082449034466126, "PlayResult": "Out", "xwOBA": 0.15721025098651248}, {"GameDate": "2026-04-05", "PitcherHand": "L", "PitchType": "Changeup", "Balls": 3, "Strikes": 1, "PlateLocHeight": 2.660457034514935, "PlateLocSide": 0.9539624393010215, "PlayResult": "Out", "xwOBA": 1.4707017846435626}, {"GameDate": "2026-04-01", "PitcherHand": "R", "PitchType": "Curveball", "Balls": 2, "Strikes": 0, "PlateLocHeight": 0.645148444032229, "PlateLocSide": 0.4518083667332704, "PlayResult": "Out", "xwOBA": 0.3130794952941351}, {"GameDate": "2026-04-15", "PitcherHand": "R", "PitchType": "Changeup", "Balls": 0, "Strikes": 2, "PlateLocHeight": 4.276563192903627, "PlateLocSide": 1.254241379764688, "PlayResult": "Out", "xwOBA": 0.09097576043195355}, {"GameDate": "2026-04-15", "PitcherHand": "L", "PitchType": "Sinker", "Balls": 3, "Strikes": 2, "PlateLocHeight": 0.9690395647777406, "PlateLocSide": 0.4654506463211956, "PlayResult": "Single", "xwOBA": 1.3299961879101039}, {"GameDate": "2026-04-05", "PitcherHand": "R", "PitchType": "Curveball", "Balls": 3, "Strikes": 2, "PlateLocHeight": 2.5007643274923357, "PlateLocSide": 0.44538790562718567, "PlayResult": "Single", "xwOBA": 0.3488831667506641}, {"GameDate": "2026-04-10", "PitcherHand": "R", "PitchType": "Sinker", "Balls": 0, "Strikes": 1, "PlateLocHeight": 1.5371753965273087, "PlateLocSide": 0.841825413751216, "PlayResult": "Out", "xwOBA": 0.9373882214403254}, {"GameDate": "2026-04-03", "PitcherHand": "L", "PitchType": "Curveball", "Balls": 0, "Strikes": 0, "PlateLocHeight": 1.5942671747170007, "PlateLocSide": -0.3538036967808531, "PlayResult": "Single", "xwOBA": 1.1183037771491073}, {"GameDate": "2026-04-05", "PitcherHand": "L", "PitchType": "Curveball", "Balls": 3, "Strikes": 2, "PlateLocHeight": 1.653651447472844, "PlateLocSide": -0.6973196225441267, "PlayResult": "Single", "xwOBA": 0.5360724325655687}, {"GameDate": "2026-04-03", "PitcherHand": "R", "PitchType": "Slider", "Balls": 2, "Strikes": 0, "PlateLocHeight": 3.5492284195674575, "PlateLocSide": 0.0730795806901754, "PlayResult": "Out", "xwOBA": 0.7799365940929164}, {"GameDate": "2026-04-10", "PitcherHand": "R", "PitchType": "Sinker", "Balls": 1, "Strikes": 1, "PlateLocHeight": 4.497673060252275, "PlateLocSide": 0.8311911668901057, "PlayResult": "Out", "xwOBA": 1.2725840538546414}, {"GameDate": "2026-04-03", "PitcherHand": "L", "PitchType": "Slider", "Balls": 3, "Strikes": 0, "PlateLocHeight": 0.7298187955330011, "PlateLocSide": 0.29810800477264765, "PlayResult": "HomeRun", "xwOBA": 1.173163832584221}, {"GameDate": "2026-04-07", "PitcherHand": "R", "PitchType": "Changeup", "Balls": 1, "Strikes": 2, "PlateLocHeight": 1.0646936913063945, "PlateLocSide": -0.08356777942425064, "PlayResult": "Double", "xwOBA": 0.7467175533449801}, {"GameDate": "2026-04-10", "PitcherHand": "L", "PitchType": "Changeup", "Balls": 1, "Strikes": 2, "PlateLocHeight": 2.1714314987956334, "PlateLocSide": 1.1466181721437367, "PlayResult": "Double", "xwOBA": 0.06909212272549903}, {"GameDate": "2026-04-10", "PitcherHand": "R", "PitchType": "Changeup", "Balls": 2, "Strikes": 1, "PlateLocHeight": 3.8374967684301255, "PlateLocSide": -0.4029472063742312, "PlayResult": "Out", "xwOBA": 0.5984135618902278}, {"GameDate": "2026-04-15", "PitcherHand": "R", "PitchType": "Slider", "Balls": 1, "Strikes": 1, "PlateLocHeight": 1.3564804554976413, "PlateLocSide": -0.9347017594085212, "PlayResult": "HomeRun", "xwOBA": 0.367861811364787}, {"GameDate": "2026-04-10", "PitcherHand": "R", "PitchType": "Slider", "Balls": 0, "Strikes": 0, "PlateLocHeight": 2.9605996286616616, "PlateLocSide": -0.145889426663512, "PlayResult": "Out", "xwOBA": 1.050069804531847}, {"GameDate": "2026-04-07", "PitcherHand": "R", "PitchType": "Fastball", "Balls": 3, "Strikes": 2, "PlateLocHeight": 2.111445630036264, "PlateLocSide": 0.09586093523470929, "PlayResult": "Out", "xwOBA": 1.0450819775626385}, {"GameDate": "2026-04-01", "PitcherHand": "R", "PitchType": "Slider", "Balls": 2, "Strikes": 0, "PlateLocHeight": 1.8662649953613184, "PlateLocSide": 0.11769249087465217, "PlayResult": "Out", "xwOBA": 0.2690899353273104}, {"GameDate": "2026-04-01", "PitcherHand": "R", "PitchType": "Sinker", "Balls": 3, "Strikes": 1, "PlateLocHeight": 3.5012282033818605, "PlateLocSide": 1.4179277311642182, "PlayResult": "Out", "xwOBA": 1.085627399898285}, {"GameDate": "2026-04-01", "PitcherHand": "R", "PitchType": "Fastball", "Balls": 1, "Strikes": 2, "PlateLocHeight": 0.8503092727141675, "PlateLocSide": 0.9654321264507093, "PlayResult": "Out", "xwOBA": 0.6536658586756945}, {"GameDate": "2026-04-15", "PitcherHand": "L", "PitchType": "Sinker", "Balls": 2, "Strikes": 0, "PlateLocHeight": 2.4481545992930163, "PlateLocSide": 1.2076230761511217, "PlayResult": "Out", "xwOBA": 0.9380806559997847}, {"GameDate": "2026-04-15", "PitcherHand": "R", "PitchType": "Curveball", "Balls": 1, "Strikes": 0, "PlateLocHeight": 1.2968078941982233, "PlateLocSide": -1.2512085660943204, "PlayResult": "Single", "xwOBA": 1.4105528859280902}, {"GameDate": "2026-04-03", "PitcherHand": "L", "PitchType": "Slider", "Balls": 0, "Strikes": 2, "PlateLocHeight": 0.7169321305821144, "PlateLocSide": -0.2814146091642784, "PlayResult": "Out", "xwOBA": 0.48526321194340616}, {"GameDate": "2026-04-07", "PitcherHand": "L", "PitchType": "Curveball", "Balls": 0, "Strikes": 0, "PlateLocHeight": 3.7519023391094284, "PlateLocSide": 1.019048106635291, "PlayResult": "HomeRun", "xwOBA": 0.026538336134212692}, {"GameDate": "2026-04-15", "PitcherHand": "R", "PitchType": "Slider", "Balls": 3, "Strikes": 1, "PlateLocHeight": 3.0304953243802903, "PlateLocSide": 1.0232871474721676, "PlayResult": "Out", "xwOBA": 1.4848265850213802}, {"GameDate": "2026-04-03", "PitcherHand": "L", "PitchType": "Slider", "Balls": 1, "Strikes": 1, "PlateLocHeight": 1.468460188966095, "PlateLocSide": 1.3416822570183076, "PlayResult": "Out", "xwOBA": 0.3854606168708015}, {"GameDate": "2026-04-03", "PitcherHand": "R", "PitchType": "Curveball", "Balls": 0, "Strikes": 0, "PlateLocHeight": 2.612147512808792, "PlateLocSide": 1.3928233126065939, "PlayResult": "HomeRun", "xwOBA": 0.6622058250376439}, {"GameDate": "2026-04-05", "PitcherHand": "L", "PitchType": "Curveball", "Balls": 3, "Strikes": 0, "PlateLocHeight": 0.5482024819235121, "PlateLocSide": 0.22671535817566157, "PlayResult": "HomeRun", "xwOBA": 0.02950369844942563}, {"GameDate": "2026-04-05", "PitcherHand": "R", "PitchType": "Curveball", "Balls": 1, "Strikes": 2, "PlateLocHeight": 2.6046238394360746, "PlateLocSide": -0.8685411359547928, "PlayResult": "Out", "xwOBA": 0.6408042297932306}, {"GameDate": "2026-04-01", "PitcherHand": "R", "PitchType": "Sinker", "Balls": 2, "Strikes": 1, "PlateLocHeight": 3.6782681366023406, "PlateLocSide": 0.3217346211735781, "PlayResult": "Single", "xwOBA": 0.6561591873523291}, {"GameDate": "2026-04-07", "PitcherHand": "R", "PitchType": "Slider", "Balls": 0, "Strikes": 2, "PlateLocHeight": 2.0592614578547503, "PlateLocSide": 1.3016724345917687, "PlayResult": "Double", "xwOBA": 0.4938365498550969}, {"GameDate": "2026-04-10", "PitcherHand": "R", "PitchType": "Slider", "Balls": 2, "Strikes": 0, "PlateLocHeight": 4.169706046643939, "PlateLocSide": 1.191575250473588, "PlayResult": "Single", "xwOBA": 0.2728532587599313}, {"GameDate": "2026-04-15", "PitcherHand": "L", "PitchType": "Curveball", "Balls": 1, "Strikes": 2, "PlateLocHeight": 0.9313329688808785, "PlateLocSide": 0.0194461737940248, "PlayResult": "Single", "xwOBA": 0.8994911582169942}, {"GameDate": "2026-04-05", "PitcherHand": "L", "PitchType": "Sinker", "Balls": 2, "Strikes": 2, "PlateLocHeight": 3.4887288722111003, "PlateLocSide": -0.5183663186319086, "PlayResult": "Out", "xwOBA": 0.15130315614828155}, {"GameDate": "2026-04-05", "PitcherHand": "R", "PitchType": "Changeup", "Balls": 0, "Strikes": 1, "PlateLocHeight": 2.851988444687255, "PlateLocSide": -1.0732290949721888, "PlayResult": "Out", "xwOBA": 0.1470363552819715}, {"GameDate": "2026-04-01", "PitcherHand": "R", "PitchType": "Changeup", "Balls": 3, "Strikes": 2, "PlateLocHeight": 2.7583365071225283, "PlateLocSide": -0.24204986265507467, "PlayResult": "Double", "xwOBA": 0.42181859136658556}, {"GameDate": "2026-04-15", "PitcherHand": "R", "PitchType": "Sinker", "Balls": 2, "Strikes": 0, "PlateLocHeight": 2.0891733725510755, "PlateLocSide": -0.9239551493811017, "PlayResult": "HomeRun", "xwOBA": 0.5032459184095415}, {"GameDate": "2026-04-10", "PitcherHand": "R", "PitchType": "Slider", "Balls": 3, "Strikes": 0, "PlateLocHeight": 0.9240821208118049, "PlateLocSide": 1.329482429017379, "PlayResult": "Out", "xwOBA": 0.5679781335425786}, {"GameDate": "2026-04-15", "PitcherHand": "L", "PitchType": "Slider", "Balls": 1, "Strikes": 0, "PlateLocHeight": 0.522124067157308, "PlateLocSide": 0.6439451436922239, "PlayResult": "Out", "xwOBA": 0.974466904173104}, {"GameDate": "2026-04-10", "PitcherHand": "R", "PitchType": "Curveball", "Balls": 2, "Strikes": 2, "PlateLocHeight": 2.5482208982230494, "PlateLocSide": -1.1033990544610466, "PlayResult": "Out", "xwOBA": 0.22808467457578135}, {"GameDate": "2026-04-15", "PitcherHand": "L", "PitchType": "Sinker", "Balls": 0, "Strikes": 1, "PlateLocHeight": 3.9055162072312397, "PlateLocSide": -0.8736980742047581, "PlayResult": "Double", "xwOBA": 0.8077214986135367}, {"GameDate": "2026-04-01", "PitcherHand": "R", "PitchType": "Curveball", "Balls": 3, "Strikes": 0, "PlateLocHeight": 3.73726673081995, "PlateLocSide": -1.3443110071965565, "PlayResult": "Double", "xwOBA": 0.7507148843974751}, {"GameDate": "2026-04-10", "PitcherHand": "R", "PitchType": "Sinker", "Balls": 0, "Strikes": 0, "PlateLocHeight": 3.643050293161815, "PlateLocSide": 0.42665089193928174, "PlayResult": "HomeRun", "xwOBA": 0.029583121967958925}, {"GameDate": "2026-04-03", "PitcherHand": "R", "PitchType": "Changeup", "Balls": 0, "Strikes": 1, "PlateLocHeight": 3.2150335418961755, "PlateLocSide": -0.3224278643964973, "PlayResult": "HomeRun", "xwOBA": 1.0417417656692713}, {"GameDate": "2026-04-07", "PitcherHand": "L", "PitchType": "Sinker", "Balls": 0, "Strikes": 1, "PlateLocHeight": 1.253292816474509, "PlateLocSide": 0.017030808587546353, "PlayResult": "Double", "xwOBA": 0.8991010845707079}, {"GameDate": "2026-04-10", "PitcherHand": "R", "PitchType": "Fastball", "Balls": 3, "Strikes": 2, "PlateLocHeight": 0.7090437801058269, "PlateLocSide": -0.17725011618274888, "PlayResult": "Out", "xwOBA": 0.4395527931633275}, {"GameDate": "2026-04-07", "PitcherHand": "L", "PitchType": "Sinker", "Balls": 3, "Strikes": 2, "PlateLocHeight": 2.1895799574609183, "PlateLocSide": 1.475024415634207, "PlayResult": "HomeRun", "xwOBA": 0.6561026276534309}, {"GameDate": "2026-04-03", "PitcherHand": "L", "PitchType": "Fastball", "Balls": 2, "Strikes": 0, "PlateLocHeight": 3.5623859549176395, "PlateLocSide": -0.08082787150306392, "PlayResult": "Double", "xwOBA": 0.18345667156193052}, {"GameDate": "2026-04-07", "PitcherHand": "L", "PitchType": "Changeup", "Balls": 3, "Strikes": 2, "PlateLocHeight": 0.7982963003734271, "PlateLocSide": 0.4197716501418669, "PlayResult": "HomeRun", "xwOBA": 0.7290779290772029}, {"GameDate": "2026-04-07", "PitcherHand": "R", "PitchType": "Changeup", "Balls": 1, "Strikes": 2, "PlateLocHeight": 3.86529566660054, "PlateLocSide": -0.2542868228077064, "PlayResult": "Single", "xwOBA": 0.3841614168332801}, {"GameDate": "2026-04-05", "PitcherHand": "R", "PitchType": "Sinker", "Balls": 0, "Strikes": 1, "PlateLocHeight": 2.4654111721117054, "PlateLocSide": 0.6081951041706537, "PlayResult": "Double", "xwOBA": 0.28201844760941047}, {"GameDate": "2026-04-15", "PitcherHand": "R", "PitchType": "Fastball", "Balls": 2, "Strikes": 1, "PlateLocHeight": 0.9652066869373561, "PlateLocSide": -1.4425089227987435, "PlayResult": "Out", "xwOBA": 1.4070874824394806}, {"GameDate": "2026-04-03", "PitcherHand": "L", "PitchType": "Curveball", "Balls": 2, "Strikes": 1, "PlateLocHeight": 2.8991833902100503, "PlateLocSide": 0.9083340352693492, "PlayResult": "HomeRun", "xwOBA": 0.4358089312739765}, {"GameDate": "2026-04-03", "PitcherHand": "R", "PitchType": "Changeup", "Balls": 2, "Strikes": 0, "PlateLocHeight": 2.357610691149123, "PlateLocSide": 0.42721504110050934, "PlayResult": "Out", "xwOBA": 0.40203018929265494}, {"GameDate": "2026-04-03", "PitcherHand": "L", "PitchType": "Curveball", "Balls": 2, "Strikes": 0, "PlateLocHeight": 1.0234657988255935, "PlateLocSide": 0.2717003690812023, "PlayResult": "Single", "xwOBA": 1.3734086929408014}, {"GameDate": "2026-04-10", "PitcherHand": "L", "PitchType": "Changeup", "Balls": 0, "Strikes": 0, "PlateLocHeight": 2.1562575374208355, "PlateLocSide": 0.48906897568684893, "PlayResult": "Out", "xwOBA": 1.4038456316126773}, {"GameDate": "2026-04-07", "PitcherHand": "R", "PitchType": "Fastball", "Balls": 2, "Strikes": 2, "PlateLocHeight": 3.6762564663150332, "PlateLocSide": 0.2706884544010706, "PlayResult": "Out", "xwOBA": 1.3158098590389276}, {"GameDate": "2026-04-05", "PitcherHand": "L", "PitchType": "Sinker", "Balls": 0, "Strikes": 0, "PlateLocHeight": 0.9264872090540437, "PlateLocSide": -1.2496035939410883, "PlayResult": "Out", "xwOBA": 0.6473763979899896}, {"GameDate": "2026-04-07", "PitcherHand": "L", "PitchType": "Sinker", "Balls": 1, "Strikes": 1, "PlateLocHeight": 2.7586862547614595, "PlateLocSide": -1.1614859333299115, "PlayResult": "HomeRun", "xwOBA": 1.1169775040248175}, {"GameDate": "2026-04-05", "PitcherHand": "L", "PitchType": "Fastball", "Balls": 0, "Strikes": 0, "PlateLocHeight": 1.3840978558617767, "PlateLocSide": 0.6879705191292089, "PlayResult": "Single", "xwOBA": 1.3327016700999832}, {"GameDate": "2026-04-07", "PitcherHand": "L", "PitchType": "Fastball", "Balls": 1, "Strikes": 1, "PlateLocHeight": 0.7275906007817161, "PlateLocSide": 0.31459082273554806, "PlayResult": "Out", "xwOBA": 0.4138534168439625}, {"GameDate": "2026-04-10", "PitcherHand": "R", "PitchType": "Curveball", "Balls": 0, "Strikes": 1, "PlateLocHeight": 2.701379351208596, "PlateLocSide": -0.9276205810913796, "PlayResult": "Out", "xwOBA": 0.8201387168125545}, {"GameDate": "2026-04-05", "PitcherHand": "R", "PitchType": "Curveball", "Balls": 2, "Strikes": 1, "PlateLocHeight": 1.732990279593658, "PlateLocSide": 1.2147223188908804, "PlayResult": "HomeRun", "xwOBA": 1.362397610167399}, {"GameDate": "2026-04-01", "PitcherHand": "L", "PitchType": "Fastball", "Balls": 2, "Strikes": 1, "PlateLocHeight": 2.3478393331685026, "PlateLocSide": -0.5275237617038617, "PlayResult": "HomeRun", "xwOBA": 0.9670757043056957}, {"GameDate": "2026-04-10", "PitcherHand": "L", "PitchType": "Changeup", "Balls": 3, "Strikes": 1, "PlateLocHeight": 2.4867396221391553, "PlateLocSide": -1.0382411589396554, "PlayResult": "Double", "xwOBA": 1.2481201134456874}, {"GameDate": "2026-04-07", "PitcherHand": "L", "PitchType": "Fastball", "Balls": 1, "Strikes": 1, "PlateLocHeight": 2.2679465387363935, "PlateLocSide": -0.8044338381739895, "PlayResult": "HomeRun", "xwOBA": 1.385972433930311}, {"GameDate": "2026-04-03", "PitcherHand": "R", "PitchType": "Fastball", "Balls": 0, "Strikes": 0, "PlateLocHeight": 0.8105048607707301, "PlateLocSide": -1.4416193531189438, "PlayResult": "Out", "xwOBA": 0.2797112354967563}, {"GameDate": "2026-04-10", "PitcherHand": "R", "PitchType": "Sinker", "Balls": 0, "Strikes": 1, "PlateLocHeight": 1.0605984213529278, "PlateLocSide": -0.9581347466498391, "PlayResult": "Double", "xwOBA": 1.4635306884940915}, {"GameDate": "2026-04-05", "PitcherHand": "R", "PitchType": "Changeup", "Balls": 1, "Strikes": 1, "PlateLocHeight": 3.2322928832205218, "PlateLocSide": -0.8970466944547516, "PlayResult": "Double", "xwOBA": 0.7934116538037675}, {"GameDate": "2026-04-05", "PitcherHand": "L", "PitchType": "Changeup", "Balls": 0, "Strikes": 2, "PlateLocHeight": 3.033341813263793, "PlateLocSide": 0.5928644133168044, "PlayResult": "Double", "xwOBA": 1.2268462133062785}, {"GameDate": "2026-04-07", "PitcherHand": "R", "PitchType": "Fastball", "Balls": 2, "Strikes": 2, "PlateLocHeight": 2.780170525492719, "PlateLocSide": -0.4301290808502731, "PlayResult": "Out", "xwOBA": 0.595148014077582}, {"GameDate": "2026-04-10", "PitcherHand": "R", "PitchType": "Slider", "Balls": 1, "Strikes": 0, "PlateLocHeight": 2.7669025312239244, "PlateLocSide": -0.07251933958911949, "PlayResult": "Single", "xwOBA": 1.076244521718357}, {"GameDate": "2026-04-15", "PitcherHand": "R", "PitchType": "Slider", "Balls": 3, "Strikes": 1, "PlateLocHeight": 2.9749256438897085, "PlateLocSide": -0.8339924617411253, "PlayResult": "Out", "xwOBA": 0.3314706141712491}, {"GameDate": "2026-04-07", "PitcherHand": "L", "PitchType": "Sinker", "Balls": 1, "Strikes": 0, "PlateLocHeight": 4.0320673879076345, "PlateLocSide": 0.6111241704554309, "PlayResult": "Out", "xwOBA": 0.2273909373060668}, {"GameDate": "2026-04-10", "PitcherHand": "R", "PitchType": "Slider", "Balls": 0, "Strikes": 1, "PlateLocHeight": 4.2031269280707, "PlateLocSide": -0.5481753254348362, "PlayResult": "Out", "xwOBA": 1.4957583807566157}, {"GameDate": "2026-04-07", "PitcherHand": "L", "PitchType": "Changeup", "Balls": 3, "Strikes": 0, "PlateLocHeight": 1.9505505316256824, "PlateLocSide": -0.8581671727490932, "PlayResult": "Out", "xwOBA": 0.19226038766010473}, {"GameDate": "2026-04-15", "PitcherHand": "R", "PitchType": "Fastball", "Balls": 3, "Strikes": 2, "PlateLocHeight": 2.1231912573206047, "PlateLocSide": -1.0388266142938205, "PlayResult": "Out", "xwOBA": 0.576353330671651}, {"GameDate": "2026-04-07", "PitcherHand": "R", "PitchType": "Changeup", "Balls": 3, "Strikes": 1, "PlateLocHeight": 1.628646113043676, "PlateLocSide": 0.7944644261336382, "PlayResult": "Out", "xwOBA": 1.4614921884227001}, {"GameDate": "2026-04-03", "PitcherHand": "L", "PitchType": "Fastball", "Balls": 1, "Strikes": 0, "PlateLocHeight": 1.3141109956335537, "PlateLocSide": 1.288981696945982, "PlayResult": "Out", "xwOBA": 0.7038808975831654}, {"GameDate": "2026-04-03", "PitcherHand": "R", "PitchType": "Curveball", "Balls": 3, "Strikes": 2, "PlateLocHeight": 3.1624550568653005, "PlateLocSide": 0.1016780610899235, "PlayResult": "Out", "xwOBA": 0.12627838587221252}, {"GameDate": "2026-04-03", "PitcherHand": "L", "PitchType": "Fastball", "Balls": 2, "Strikes": 1, "PlateLocHeight": 3.7012214735729008, "PlateLocSide": 0.7761025774829404, "PlayResult": "Out", "xwOBA": 1.00953402032328}, {"GameDate": "2026-04-01", "PitcherHand": "R", "PitchType": "Curveball", "Balls": 0, "Strikes": 1, "PlateLocHeight": 0.6054288616591013, "PlateLocSide": -0.8369973195289017, "PlayResult": "HomeRun", "xwOBA": 0.06083333432959526}, {"GameDate": "2026-04-05", "PitcherHand": "L", "PitchType": "Fastball", "Balls": 2, "Strikes": 2, "PlateLocHeight": 2.198627145866523, "PlateLocSide": -0.055738844503290474, "PlayResult": "Out", "xwOBA": 0.6442554475054436}, {"GameDate": "2026-04-15", "PitcherHand": "L", "PitchType": "Slider", "Balls": 3, "Strikes": 2, "PlateLocHeight": 0.78035389941651, "PlateLocSide": 0.19149266842867307, "PlayResult": "Out", "xwOBA": 0.3054668702938827}, {"GameDate": "2026-04-01", "PitcherHand": "R", "PitchType": "Fastball", "Balls": 2, "Strikes": 1, "PlateLocHeight": 2.819411473746298, "PlateLocSide": -0.7533888287140224, "PlayResult": "Single", "xwOBA": 0.7637932166768017}, {"GameDate": "2026-04-05", "PitcherHand": "L", "PitchType": "Fastball", "Balls": 0, "Strikes": 2, "PlateLocHeight": 0.9939987651957973, "PlateLocSide": -0.7123521089187131, "PlayResult": "Out", "xwOBA": 1.400204164410593}, {"GameDate": "2026-04-07", "PitcherHand": "R", "PitchType": "Changeup", "Balls": 2, "Strikes": 2, "PlateLocHeight": 1.2911983716791524, "PlateLocSide": -0.8812897125928953, "PlayResult": "HomeRun", "xwOBA": 1.4197366820174209}, {"GameDate": "2026-04-03", "PitcherHand": "R", "PitchType": "Curveball", "Balls": 1, "Strikes": 0, "PlateLocHeight": 3.4870347651912, "PlateLocSide": -1.2083163330854005, "PlayResult": "Single", "xwOBA": 1.3748096342276432}, {"GameDate": "2026-04-05", "PitcherHand": "R", "PitchType": "Curveball", "Balls": 1, "Strikes": 1, "PlateLocHeight": 4.020528097279387, "PlateLocSide": -1.2724368367169934, "PlayResult": "Single", "xwOBA": 0.5715001127390933}, {"GameDate": "2026-04-03", "PitcherHand": "R", "PitchType": "Curveball", "Balls": 0, "Strikes": 1, "PlateLocHeight": 1.1001093610521466, "PlateLocSide": -0.000117731246015218, "PlayResult": "HomeRun", "xwOBA": 0.2641107329467949}, {"GameDate": "2026-04-07", "PitcherHand": "R", "PitchType": "Changeup", "Balls": 3, "Strikes": 2, "PlateLocHeight": 2.207590501735341, "PlateLocSide": -0.734597149733745, "PlayResult": "Out", "xwOBA": 0.12141159054164824}, {"GameDate": "2026-04-01", "PitcherHand": "L", "PitchType": "Curveball", "Balls": 2, "Strikes": 2, "PlateLocHeight": 0.7259551466701804, "PlateLocSide": 0.6674354749326064, "PlayResult": "Out", "xwOBA": 0.7010718877219586}, {"GameDate": "2026-04-03", "PitcherHand": "L", "PitchType": "Changeup", "Balls": 1, "Strikes": 0, "PlateLocHeight": 3.214499286512988, "PlateLocSide": 1.024807718041611, "PlayResult": "Out", "xwOBA": 0.04905703180351623}, {"GameDate": "2026-04-01", "PitcherHand": "L", "PitchType": "Sinker", "Balls": 0, "Strikes": 1, "PlateLocHeight": 2.550785943386145, "PlateLocSide": 0.9600179337973493, "PlayResult": "Out", "xwOBA": 1.3039311837369914}, {"GameDate": "2026-04-03", "PitcherHand": "R", "PitchType": "Sinker", "Balls": 2, "Strikes": 0, "PlateLocHeight": 2.9993072270704553, "PlateLocSide": -0.3861429219897732, "PlayResult": "HomeRun", "xwOBA": 0.7664622797479883}, {"GameDate": "2026-04-05", "PitcherHand": "L", "PitchType": "Changeup", "Balls": 2, "Strikes": 0, "PlateLocHeight": 0.9542319272939408, "PlateLocSide": -1.3350997375579463, "PlayResult": "Double", "xwOBA": 0.8689779917752513}, {"GameDate": "2026-04-01", "PitcherHand": "R", "PitchType": "Fastball", "Balls": 0, "Strikes": 1, "PlateLocHeight": 2.4833929544754145, "PlateLocSide": -1.3318062030907103, "PlayResult": "HomeRun", "xwOBA": 1.2042688161896462}, {"GameDate": "2026-04-03", "PitcherHand": "R", "PitchType": "Curveball", "Balls": 1, "Strikes": 1, "PlateLocHeight": 2.6805673644531347, "PlateLocSide": 1.1706834454571524, "PlayResult": "Out", "xwOBA": 1.1158145615289379}, {"GameDate": "2026-04-01", "PitcherHand": "L", "PitchType": "Fastball", "Balls": 2, "Strikes": 1, "PlateLocHeight": 1.570484180372159, "PlateLocSide": -0.4497217574910719, "PlayResult": "Out", "xwOBA": 0.06303982411778969}, {"GameDate": "2026-04-05", "PitcherHand": "L", "PitchType": "Sinker", "Balls": 3, "Strikes": 1, "PlateLocHeight": 1.7483947695300732, "PlateLocSide": 0.7153289156724147, "PlayResult": "Out", "xwOBA": 1.3117338152786349}, {"GameDate": "2026-04-15", "PitcherHand": "R", "PitchType": "Curveball", "Balls": 1, "Strikes": 1, "PlateLocHeight": 0.7901900431528355, "PlateLocSide": 1.04448648433997, "PlayResult": "HomeRun", "xwOBA": 0.8758027480959523}, {"GameDate": "2026-04-01", "PitcherHand": "R", "PitchType": "Changeup", "Balls": 0, "Strikes": 2, "PlateLocHeight": 1.9412544163641279, "PlateLocSide": 1.3179644955526868, "PlayResult": "Single", "xwOBA": 1.2815757107517813}]}